[{"__symbolic":"module","version":4,"metadata":{"DateTimePickerOverlay":{"__symbolic":"class","decorators":[{"__symbolic":"call","expression":{"__symbolic":"reference","module":"@angular/core","name":"Component","line":20,"character":1},"arguments":[{"selector":"ionx-datetime-overlay","template":"\n        <ion-header>\n            <ion-toolbar>\n                <ion-buttons slot=\"start\">\n                    <ion-button (click)=\"cancelClicked()\" fill=\"clear\">\n                        <ion-icon name=\"close\" slot=\"icon-only\"></ion-icon>\n                    </ion-button>\n                </ion-buttons>\n\n                <ion-title>{{title}}</ion-title>                \n\n                <ion-buttons slot=\"end\">\n                    <ion-button (click)=\"doneClicked()\">{{\"@co.mmons/js-intl#Done\" | intlMessage}}</ion-button>\n                </ion-buttons>\n            </ion-toolbar>\n            <ion-toolbar>\n                <ion-segment [(ngModel)]=\"dateView\" (ionChange)=\"dateViewChanged()\">\n                    <ion-segment-button *ngFor=\"let view of dateViews\" [value]=\"view.id\">{{view.label}}</ion-segment-button>\n                </ion-segment>\n            </ion-toolbar>\n        </ion-header>\n        <ion-content>\n            \n            <div>\n\n                <ion-row ionx--values-header>\n                    <ion-col size=\"3\">\n                        <ion-button fill=\"clear\" (click)=\"dateViewMove(-1)\">\n                            <ion-icon name=\"arrow-dropleft\" slot=\"icon-only\"></ion-icon>\n                        </ion-button>\n                    </ion-col>\n                    <ion-col size=\"6\" text-center>{{dateHeader}}</ion-col>\n                    <ion-col size=\"3\" text-right>\n                        <ion-button fill=\"clear\" (click)=\"dateViewMove(1)\">\n                            <ion-icon name=\"arrow-dropright\" slot=\"icon-only\"></ion-icon>\n                        </ion-button>\n                    </ion-col>\n                </ion-row>\n                \n                <ion-row ionx--values-grid style=\"margin: 0px 14px\">\n                    <ion-col *ngFor=\"let value of dateValues\" [size]=\"dateView == 'years' ? 3 : (dateView == 'months' ? 6 : 2)\" [style.visibility]=\"value.hidden ? 'hidden' : 'visible'\">\n                        <ion-button [fill]=\"!value.checked ? 'outline' : 'solid'\" (click)=\"dateValueClicked(value.id)\">\n                            <div>\n                                <div>{{value.label}}</div>\n                                <small *ngIf=\"value.sublabel\">{{value.sublabel}}</small>\n                            </div>\n                        </ion-button>\n                    </ion-col>\n                    <ion-col size=\"6\" *ngIf=\"dateView == 'days'\">\n                        <ion-button (click)=\"todayClicked()\">{{\"@co.mmons/ionic-extensions#Today\" | intlMessage}}</ion-button>\n                    </ion-col>\n                </ion-row>\n                \n            </div>\n\n        </ion-content>\n        \n        <ion-footer *ngIf=\"timeVisible\">\n            <ion-toolbar>\n                <ion-row>\n                    <ion-col size=\"3\">\n                        <ion-input type=\"number\" [(ngModel)]=\"timeHoursFormatted\" [min]=\"0\" [max]=\"23\" inputmode=\"numeric\"></ion-input>\n                    </ion-col>\n                    <ion-col>\n                        <ion-range [(ngModel)]=\"timeHours\" min=\"0\" max=\"23\" step=\"1\"></ion-range>                \n                    </ion-col>\n                </ion-row>\n                <ion-row>\n                    <ion-col size=\"3\">\n                        <ion-input type=\"number\" [(ngModel)]=\"timeMinutesFormatted\" [min]=\"0\" [max]=\"59\" inputmode=\"numeric\"></ion-input>\n                    </ion-col>\n                    <ion-col>\n                        <ion-range [(ngModel)]=\"timeMinutes\" min=\"0\" max=\"59\" step=\"1\"></ion-range>                \n                    </ion-col>\n                </ion-row>\n                <ion-row *ngIf=\"!timezoneDisabled\">\n                    <ion-col size=\"3\"></ion-col>\n                    <ion-col size=\"9\">\n                        <ionx-select [options]=\"timezones\" [(ngModel)]=\"timezone\" overlay=\"modal\" [title]=\"'@co.mmons/ionic-extensions#Time zone' | intlMessage\" [placeholder]=\"'@co.mmons/ionic-extensions#No time zone' | intlMessage\"></ionx-select>\n                    </ion-col>\n                </ion-row>\n            </ion-toolbar>\n        </ion-footer>\n    ","styles":["\n            :host {\n                display: flex;\n            }\n\n            :host [ionx--values-header] {\n                margin: 16px 16px 8px 16px;\n            }\n\n            :host-context(.ios) [ionx--values-header] {\n                margin-top: 0px;\n                margin-bottom: 0px;\n            }\n            \n            :host [ionx--values-header] ion-col {\n                padding: 0px;\n                align-self: center;\n            }\n\n            :host [ionx--values-header] ion-button {\n                max-height: 36px;\n            }\n            \n            :host [ionx--values-grid] ion-col {\n                display: flex;\n                padding: 4px;\n                align-items: center;\n                justify-content: center;\n            }\n            \n            :host [ionx--values-grid] ion-button {\n                --box-shadow: none;\n                padding: 0px;\n                margin: 0px;\n                flex: 1;\n                display: flex;\n                --width: 100%;\n                --padding-start: 2px;\n                --padding-end: 2px;\n                --padding-top: 2px;\n                --padding-bottom: 2px;\n                --margin-start: 0px;\n                --margin-end: 0px;\n                --margin-top: 0px;\n                --margin-bottom: 0px;\n            }\n\n            :host [ionx--values-grid] ion-button div {\n                min-width: 40px;\n                line-height: 0.8;\n            }\n            \n            :host-context(.md) [ionx--values-grid] ion-button.button-outline {\n                --border-width: 1px;\n            }\n            \n            :host-context(.ios) [ionx--values-grid] ion-button {\n                --padding-start: 0px;\n                --padding-end: 0px;\n                --padding-top: 0px;\n                --padding-bottom: 0px;\n                --margin-start: 0px;\n                --margin-end: 0px;\n                --margin-top: 0px;\n                --margin-bottom: 0px;\n            }\n            \n            :host ion-footer ion-toolbar {\n                --padding-start: 16px;\n                --padding-end: 16px;\n                --padding-top: 0px;\n                --padding-bottom: 0px;\n            }\n\n            :host ion-footer ion-range {\n                padding: 0px 8px 0px 0px;\n            }\n            \n            :host ion-footer ion-input {\n                --padding-end: 8px;\n                --padding-start: 0px;\n                text-align: center;\n            }\n            \n            :host ion-footer ion-col {\n                padding: 0px;\n                align-self: center;\n            }\n            \n            :host ion-footer ionx-select {\n                padding-left: 0px;\n            }\n        "]}]}],"members":{"__ctor__":[{"__symbolic":"constructor","parameters":[{"__symbolic":"reference","module":"@ionic/angular","name":"ModalController","line":204,"character":40},{"__symbolic":"reference","module":"@co.mmons/angular-intl","name":"IntlService","line":204,"character":71},{"__symbolic":"reference","module":"@angular/core","name":"ChangeDetectorRef","line":204,"character":108}]}],"value":[{"__symbolic":"property","decorators":[{"__symbolic":"call","expression":{"__symbolic":"reference","module":"@angular/core","name":"Input","line":207,"character":5}}]}],"formatOptions":[{"__symbolic":"property","decorators":[{"__symbolic":"call","expression":{"__symbolic":"reference","module":"@angular/core","name":"Input","line":210,"character":5}}]}],"title":[{"__symbolic":"property","decorators":[{"__symbolic":"call","expression":{"__symbolic":"reference","module":"@angular/core","name":"Input","line":213,"character":5}}]}],"timezone":[{"__symbolic":"property","decorators":[{"__symbolic":"call","expression":{"__symbolic":"reference","module":"@angular/core","name":"Input","line":216,"character":5}}]}],"timezoneDisabled":[{"__symbolic":"property","decorators":[{"__symbolic":"call","expression":{"__symbolic":"reference","module":"@angular/core","name":"Input","line":219,"character":5}}]}],"dateViewChanged":[{"__symbolic":"method"}],"dateViewMove":[{"__symbolic":"method"}],"dateValueClicked":[{"__symbolic":"method"}],"generateDateValues":[{"__symbolic":"method"}],"generateDateHeader":[{"__symbolic":"method"}],"formatTime":[{"__symbolic":"method"}],"todayClicked":[{"__symbolic":"method"}],"cancelClicked":[{"__symbolic":"method"}],"doneClicked":[{"__symbolic":"method"}],"loadTimezones":[{"__symbolic":"method"}],"ngOnInit":[{"__symbolic":"method"}]}}}}]